generator_to_file/__init__.py
generator_to_file-0.0.1b3.dist-info/LICENSE
generator_to_file-0.0.1b3.dist-info/METADATA
generator_to_file-0.0.1b3.dist-info/WHEEL
generator_to_file-0.0.1b3.dist-info/top_level.txt
generator_to_file-0.0.1b3.dist-info/RECORD
