Metadata-Version: 2.1
Name: generator-to-file
Version: 0.0.1b3
Summary: Business research tools
Home-page: https://github.com/paris0120/generator_to_file
Author: Paris Liu
Author-email: paris0120@gmail.com
License: UNKNOWN
Platform: UNKNOWN
Classifier: Programming Language :: Python :: 3
Classifier: License :: OSI Approved :: GNU General Public License v3 or later (GPLv3+)
Classifier: Operating System :: OS Independent
Requires-Python: >=3.6
